storage3/__init__.py
storage3/_async/__init__.py
storage3/_async/bucket.py
storage3/_async/client.py
storage3/_async/file_api.py
storage3/_sync/__init__.py
storage3/_sync/bucket.py
storage3/_sync/client.py
storage3/_sync/file_api.py
storage3/constants.py
storage3/exceptions.py
storage3/py.typed
storage3/types.py
storage3/utils.py
storage3/version.py
storage3-2.23.1.dist-info/WHEEL
storage3-2.23.1.dist-info/METADATA
storage3-2.23.1.dist-info/RECORD
