Metadata-Version: 2.4
Name: storage3
Version: 2.23.1
Summary: Supabase Storage client for Python.
Author: Joel Lee, Leon Fedden, Daniel Reinón García, Leynier Gutiérrez González, Anand Krishna
Author-email: Joel Lee <joel@joellee.org>, Leon Fedden <leonfedden@gmail.com>, Daniel Reinón García <danielreinon@outlook.com>, Leynier Gutiérrez González <leynier41@gmail.com>, Anand Krishna <anand2312@proton.me>
License-Expression: MIT
Classifier: Programming Language :: Python :: 3
Classifier: License :: OSI Approved :: MIT License
Classifier: Operating System :: OS Independent
Requires-Dist: httpx[http2]>=0.26,<0.29
Requires-Dist: deprecation>=2.1.0
Requires-Dist: pydantic>=2.11.7
Requires-Dist: yarl>=1.20.1
Maintainer: Leonardo Santiago
Maintainer-email: Leonardo Santiago <leonardo.santiago@supabase.io>
Requires-Python: >=3.9
Project-URL: changelog, https://github.com/supabase/supabase-py/tree/main/CHANGELOG.md
Project-URL: documentation, https://supabase.github.io/storage-py
Project-URL: homepage, https://supabase.github.io/storage-py
Project-URL: repository, https://github.com/supabase/supabase-py
